Metadata-Version: 2.4
Name: pymexc
Version: 1.2.17
Summary: Unofficial python library for interacting with the MEXC crypto exchange
Home-page: https://github.com/makarworld/pymexc.git
Download-URL: https://github.com/makarworld/pymexc/archive/refs/tags/v1.2.17.zip
Author: abuztrade
Author-email: abuztrade.work@gmail.com
License: MIT
Project-URL: Bug Reports, https://github.com/makarworld/pymexc/issues
Project-URL: Source, https://github.com/makarworld/pymexc
Keywords: mexc,mexc api,mexc api v1,mexc futures bypass,mexc api v2,mexc api v3,mexc spot,mexc futures,mexc websocket,mexc http,mexc rest
Classifier: Development Status :: 4 - Beta
Classifier: Topic :: Communications :: Email
Classifier: Operating System :: OS Independent
Classifier: License :: OSI Approved :: MIT License
Classifier: Programming Language :: Python :: 3.12
Classifier: Intended Audience :: Developers
Classifier: Intended Audience :: Customer Service
Classifier: Intended Audience :: Financial and Insurance Industry
Requires-Python: >=3.9.0
License-File: LICENSE
Requires-Dist: websocket-client
Requires-Dist: curl-cffi
Requires-Dist: wsaccel
Requires-Dist: websockets
Requires-Dist: protobuf
Requires-Dist: python-dotenv
Requires-Dist: pytest
Requires-Dist: pytest-asyncio
Requires-Dist: aiohttp
Dynamic: author
Dynamic: author-email
Dynamic: classifier
Dynamic: description
Dynamic: description-content-type
Dynamic: download-url
Dynamic: home-page
Dynamic: keywords
Dynamic: license
Dynamic: license-file
Dynamic: project-url
Dynamic: requires-dist
Dynamic: requires-python
Dynamic: summary
